Metadata-Version: 1.1
Name: flux-workflows
Version: 0.0.3
Summary: Command line tool for interacting with Flux Workflows
Home-page: http://www.ntt.com
Author: NTT communications
Author-email: michael.tonks@headforwards.com
License: GNU General Public License v2 (GPLv2)
Platform: UNKNOWN
Classifier: Development Status :: 4 - Beta
Classifier: Environment :: Console
Classifier: Intended Audience :: Developers
Classifier: License :: OSI Approved :: GNU General Public License v2 (GPLv2)
Classifier: Natural Language :: English
Classifier: Programming Language :: Python :: 2 :: Only
Classifier: Programming Language :: Python :: 2.7
Classifier: Topic :: Software Development
